COPYING
MANIFEST.in
README.rst
setup.py
doc/Makefile
doc/conf.py
doc/index.rst
doc/logo.png
doc/references.rst
doc/releases.rst
doc/tamkin_workflow.png
doc/tst.png
doc/tst_2d.png
doc/_build/html/_images/5t.png
doc/_build/html/_images/arrhenius_bimolecular_gas_phase.png
doc/_build/html/_images/inheritance-34d3456b3092ca2152263859810cea18915fb69a.png
doc/_build/html/_images/inheritance-3af4b8c3602f9029844070f0c9eb40248a2019e4.png
doc/_build/html/_images/inheritance-92f049696a4e500d9e6b205dd80bd85119607ceb.png
doc/_build/html/_images/inheritance-e39a79ab524c11cfd4e4245accf6e7336f1af2b1.png
doc/_build/html/_images/tamkin_workflow.png
doc/_build/html/_images/tst.png
doc/_build/html/_images/tst_2d.png
doc/_build/html/_static/comment-bright.png
doc/_build/html/_static/comment-close.png
doc/_build/html/_static/comment.png
doc/_build/html/_static/down-pressed.png
doc/_build/html/_static/down.png
doc/_build/html/_static/file.png
doc/_build/html/_static/logo.png
doc/_build/html/_static/minus.png
doc/_build/html/_static/plus.png
doc/_build/html/_static/up-pressed.png
doc/_build/html/_static/up.png
doc/reference/aux.rst
doc/reference/io.rst
doc/reference/nma.rst
doc/reference/pf.rst
doc/reference/tamkin-driver.rst
doc/tutorial/5t.png
doc/tutorial/arrhenius_bimolecular_gas_phase.png
doc/tutorial/chemphys_advanced.rst
doc/tutorial/chemphys_examples.rst
doc/tutorial/chemphys_tamkin.rst
doc/tutorial/chemphys_theory.rst
doc/tutorial/cite.rst
doc/tutorial/data.rst
doc/tutorial/development.rst
doc/tutorial/getting_started.rst
doc/tutorial/install.rst
doc/tutorial/support.rst
tamkin/__init__.py
tamkin/chemmod.py
tamkin/data.py
tamkin/driver.py
tamkin/geom.py
tamkin/nma.py
tamkin/nmatools.py
tamkin/partf.py
tamkin/pftools.py
tamkin/rotor.py
tamkin/timer.py
tamkin/tunneling.py
tamkin/version.py
tamkin.egg-info/PKG-INFO
tamkin.egg-info/SOURCES.txt
tamkin.egg-info/dependency_links.txt
tamkin.egg-info/entry_points.txt
tamkin.egg-info/requires.txt
tamkin.egg-info/top_level.txt
tamkin/data/test/an/butane.cis.freq.fchk
tamkin/data/test/an/ethanol.2.cor
tamkin/data/test/an/ethanol.cor
tamkin/data/test/an/ethanol.hess.full
tamkin/data/test/an/ethanol.modes.full
