Metadata-Version: 1.1
Name: tamkin
Version: 1.2.6
Summary: TAMkin is a post-processing toolkit for thermochemistry and kinetics analysis.
Home-page: https://github.com/molmod/tamkin
Author: Toon Verstraelen, Matthias Vandichel, An Ghysels
Author-email: Toon.Verstraelen@UGent.be, Matthias.Vandichel@UGent.be, An.Ghysels@UGent.be
License: UNKNOWN
Platform: UNKNOWN
Classifier: Environment :: Console
Classifier: License :: OSI Approved :: GNU General Public License v3 or later (GPLv3+)
Classifier: Operating System :: POSIX :: Linux
Classifier: Programming Language :: Python :: 2.7
Classifier: Programming Language :: Python :: 3
Classifier: Programming Language :: Python :: 3.6
Classifier: Programming Language :: Python :: 3.7
Classifier: Topic :: Scientific/Engineering :: Physics
Classifier: Topic :: Scientific/Engineering :: Chemistry
Classifier: Intended Audience :: Science/Research
